cht_observations/__init__.py
cht_observations/_ndbc.py
cht_observations/_noaa_coops.py
cht_observations/observation_stations.py
cht_observations/utils.py
cht_observations-0.2.1.dist-info/LICENSE
cht_observations-0.2.1.dist-info/METADATA
cht_observations-0.2.1.dist-info/WHEEL
cht_observations-0.2.1.dist-info/top_level.txt
cht_observations-0.2.1.dist-info/zip-safe
cht_observations-0.2.1.dist-info/RECORD
