Metadata-Version: 2.2
Name: cht_observations
Version: 0.2.1
Summary: Download tide gauge observation data
Author-email: Maarten van Ormondt <maarten.vanormondt@deltares.nl>, Julian Hofer <Julian.Hofer@deltares.nl>, Sarwan Peiter <Sarwan.Peiter@deltares.nl>
License: MIT
Project-URL: Source, https://github.com/Deltares/cht_observations
Classifier: Intended Audience :: Science/Research
Classifier: Topic :: Scientific/Engineering :: Hydrology
Requires-Python: >=3.10
License-File: LICENSE
Requires-Dist: NDBC
Requires-Dist: noaa_coops
Requires-Dist: geopandas
Provides-Extra: tests
Requires-Dist: pytest; extra == "tests"
